config_yml/__init__.py
config_yml/config.py
tests/__init__.py
tests/test_config.py
tests/data/__init__.py
tests/data/config_existing.yml
tests/data/config_template.yml
config_yml-0.3.1.dist-info/METADATA
config_yml-0.3.1.dist-info/WHEEL
config_yml-0.3.1.dist-info/top_level.txt
config_yml-0.3.1.dist-info/RECORD
