Metadata-Version: 2.1
Name: config-yml
Version: 0.3.1
Summary: Utility modules for Class management
Home-page: https://github.com/Phornee/config_yml
Author: Ismael Raya
Author-email: phornee@gmail.com
License: UNKNOWN
Platform: UNKNOWN
Classifier: Programming Language :: Python :: 3
Classifier: License :: OSI Approved :: MIT License
Classifier: Operating System :: OS Independent
Requires-Python: >=3.6
Requires-Dist: PyYAML (>=5.3.1)
